MANIFEST.in
setup.py
karl_pkg/__init__.py
karl_pkg.egg-info/PKG-INFO
karl_pkg.egg-info/SOURCES.txt
karl_pkg.egg-info/dependency_links.txt
karl_pkg.egg-info/entry_points.txt
karl_pkg.egg-info/requires.txt
karl_pkg.egg-info/top_level.txt
karl_pkg/cmd/__init__.py
karl_pkg/cmd/print_cmd.py