Metadata-Version: 1.0
Name: karl-pkg
Version: 1.0.0
Summary: karl python package sample
Home-page: UNKNOWN
Author: karl
Author-email: karl@karl.com
License: UNKNOWN
Platform: UNKNOWN
